napari_curtain/__init__.py
napari_curtain/_function.py
napari_curtain/_tests/__init__.py
napari_curtain/_tests/test_function.py
napari_curtain-0.1.1.dist-info/LICENSE
napari_curtain-0.1.1.dist-info/METADATA
napari_curtain-0.1.1.dist-info/WHEEL
napari_curtain-0.1.1.dist-info/entry_points.txt
napari_curtain-0.1.1.dist-info/top_level.txt
napari_curtain-0.1.1.dist-info/RECORD
