Metadata-Version: 2.1
Name: napari-curtain
Version: 0.1.1
Summary: View one image over another as curtain
Home-page: https://github.com/haesleinhuepf/napari-curtain
Author: Robert Haase
Author-email: robert.haase@tu-dresden.de
License: BSD-3-Clause
Project-URL: Bug Tracker, https://github.com/haesleinhuepf/napari-curtain/issues
Project-URL: Documentation, https://github.com/haesleinhuepf/napari-curtain#README.md
Project-URL: Source Code, https://github.com/haesleinhuepf/napari-curtain
Project-URL: User Support, https://github.com/haesleinhuepf/napari-curtain/issues
Platform: UNKNOWN
Classifier: Development Status :: 3 - Alpha
Classifier: Intended Audience :: Developers
Classifier: Framework :: napari
Classifier: Topic :: Scientific/Engineering :: Image Processing
Classifier: Programming Language :: Python
Classifier: Programming Language :: Python :: 3
Classifier: Programming Language :: Python :: 3.7
Classifier: Programming Language :: Python :: 3.8
Classifier: Programming Language :: Python :: 3.9
Classifier: Operating System :: OS Independent
Classifier: License :: OSI Approved :: BSD License
Requires-Python: >=3.7
License-File: LICENSE
Requires-Dist: napari-plugin-engine (>=0.1.4)
Requires-Dist: numpy
Requires-Dist: napari-tools-menu
